[
  {
    "name": "friend1",
    "display_name": "เพื่อน 1",
    "message": "ยินดีกับความสำเร็จในการรับปริญญา! ขอให้อนาคตของ friend1 สดใสและก้าวหน้า 🎓",
    "theme": "random",
    "photos": [
      "assets/friends/friend1/1.jpg",
      "assets/friends/friend1/2.jpg",
      "assets/friends/friend1/3.jpg"
    ]
  },
  {
    "name": "friend2",
    "display_name": "เพื่อน 2",
    "message": "ยินดีกับความสำเร็จในการรับปริญญา! ขอให้อนาคตของ friend2 สดใสและก้าวหน้า 🎓",
    "theme": "random",
    "photos": [
      "assets/friends/friend2/1.jpg",
      "assets/friends/friend2/2.jpg",
      "assets/friends/friend2/3.jpg"
    ]
  },
  {
    "name": "friend3",
    "display_name": "เพื่อน 3",
    "message": "ยินดีกับความสำเร็จในการรับปริญญา! ขอให้อนาคตของ friend3 สดใสและก้าวหน้า 🎓",
    "theme": "random",
    "photos": [
      "assets/friends/friend3/1.jpg",
      "assets/friends/friend3/2.jpg",
      "assets/friends/friend3/3.jpg"
    ]
  },
  {
    "name": "friend4",
    "display_name": "เพื่อน 4",
    "message": "ยินดีกับความสำเร็จในการรับปริญญา! ขอให้อนาคตของ friend4 สดใสและก้าวหน้า 🎓",
    "theme": "random",
    "photos": [
      "assets/friends/friend4/1.jpg",
      "assets/friends/friend4/2.jpg",
      "assets/friends/friend4/3.jpg"
    ]
  },
  {
    "name": "friend5",
    "display_name": "เพื่อน 5",
    "message": "ยินดีกับความสำเร็จในการรับปริญญา! ขอให้อนาคตของ friend5 สดใสและก้าวหน้า 🎓",
    "theme": "random",
    "photos": [
      "assets/friends/friend5/1.jpg",
      "assets/friends/friend5/2.jpg",
      "assets/friends/friend5/3.jpg"
    ]
  },
  {
    "name": "friend6",
    "display_name": "เพื่อน 6",
    "message": "ยินดีกับความสำเร็จในการรับปริญญา! ขอให้อนาคตของ friend6 สดใสและก้าวหน้า 🎓",
    "theme": "random",
    "photos": [
      "assets/friends/friend6/1.jpg",
      "assets/friends/friend6/2.jpg",
      "assets/friends/friend6/3.jpg"
    ]
  },
  {
    "name": "friend7",
    "display_name": "เพื่อน 7",
    "message": "ยินดีกับความสำเร็จในการรับปริญญา! ขอให้อนาคตของ friend7 สดใสและก้าวหน้า 🎓",
    "theme": "random",
    "photos": [
      "assets/friends/friend7/1.jpg",
      "assets/friends/friend7/2.jpg",
      "assets/friends/friend7/3.jpg"
    ]
  },
  {
    "name": "friend8",
    "display_name": "เพื่อน 8",
    "message": "ยินดีกับความสำเร็จในการรับปริญญา! ขอให้อนาคตของ friend8 สดใสและก้าวหน้า 🎓",
    "theme": "random",
    "photos": [
      "assets/friends/friend8/1.jpg",
      "assets/friends/friend8/2.jpg",
      "assets/friends/friend8/3.jpg"
    ]
  },
  {
    "name": "friend9",
    "display_name": "เพื่อน 9",
    "message": "ยินดีกับความสำเร็จในการรับปริญญา! ขอให้อนาคตของ friend9 สดใสและก้าวหน้า 🎓",
    "theme": "random",
    "photos": [
      "assets/friends/friend9/1.jpg",
      "assets/friends/friend9/2.jpg",
      "assets/friends/friend9/3.jpg"
    ]
  },
  {
    "name": "friend10",
    "display_name": "เพื่อน 10",
    "message": "ยินดีกับความสำเร็จในการรับปริญญา! ขอให้อนาคตของ friend10 สดใสและก้าวหน้า 🎓",
    "theme": "random",
    "photos": [
      "assets/friends/friend10/1.jpg",
      "assets/friends/friend10/2.jpg",
      "assets/friends/friend10/3.jpg"
    ]
  },
  {
    "name": "friend11",
    "display_name": "เพื่อน 11",
    "message": "ยินดีกับความสำเร็จในการรับปริญญา! ขอให้อนาคตของ friend11 สดใสและก้าวหน้า 🎓",
    "theme": "random",
    "photos": [
      "assets/friends/friend11/1.jpg",
      "assets/friends/friend11/2.jpg",
      "assets/friends/friend11/3.jpg"
    ]
  },
  {
    "name": "friend12",
    "display_name": "เพื่อน 12",
    "message": "ยินดีกับความสำเร็จในการรับปริญญา! ขอให้อนาคตของ friend12 สดใสและก้าวหน้า 🎓",
    "theme": "random",
    "photos": [
      "assets/friends/friend12/1.jpg",
      "assets/friends/friend12/2.jpg",
      "assets/friends/friend12/3.jpg"
    ]
  },
  {
    "name": "friend13",
    "display_name": "เพื่อน 13",
    "message": "ยินดีกับความสำเร็จในการรับปริญญา! ขอให้อนาคตของ friend13 สดใสและก้าวหน้า 🎓",
    "theme": "random",
    "photos": [
      "assets/friends/friend13/1.jpg",
      "assets/friends/friend13/2.jpg",
      "assets/friends/friend13/3.jpg"
    ]
  },
  {
    "name": "friend14",
    "display_name": "เพื่อน 14",
    "message": "ยินดีกับความสำเร็จในการรับปริญญา! ขอให้อนาคตของ friend14 สดใสและก้าวหน้า 🎓",
    "theme": "random",
    "photos": [
      "assets/friends/friend14/1.jpg",
      "assets/friends/friend14/2.jpg",
      "assets/friends/friend14/3.jpg"
    ]
  },
  {
    "name": "friend15",
    "display_name": "เพื่อน 15",
    "message": "ยินดีกับความสำเร็จในการรับปริญญา! ขอให้อนาคตของ friend15 สดใสและก้าวหน้า 🎓",
    "theme": "random",
    "photos": [
      "assets/friends/friend15/1.jpg",
      "assets/friends/friend15/2.jpg",
      "assets/friends/friend15/3.jpg"
    ]
  }
]